Metadata-Version: 2.1
Name: thaifortrading
Version: 0.0.5
Summary: Collections of Thai for trading codes
Home-page: UNKNOWN
Author: Chayaphon Tanwongvarl
Author-email: chayaphont@yahoo.co.uk
License: UNKNOWN
Platform: UNKNOWN
Classifier: Programming Language :: Python :: 3
Classifier: License :: OSI Approved :: MIT License
Classifier: Operating System :: OS Independent
